seeact/__init__.py
seeact/agent.py
seeact/mark_page.js
seeact/data_utils/__init__.py
seeact/data_utils/format_prompt_utils.py
seeact/data_utils/prompts.py
seeact/demo_utils/__init__.py
seeact/demo_utils/browser_helper.py
seeact/demo_utils/crawler_helper.py
seeact/demo_utils/format_prompt.py
seeact/demo_utils/inference_engine.py
seeact-0.2.9.0.dist-info/LICENSE
seeact-0.2.9.0.dist-info/METADATA
seeact-0.2.9.0.dist-info/WHEEL
seeact-0.2.9.0.dist-info/top_level.txt
seeact-0.2.9.0.dist-info/RECORD
