Metadata-Version: 2.2
Name: seeact
Version: 0.2.9.0
Summary: SeeAct is a system for generalist web agents that autonomously carry out tasks on any given website, with a focus on large multimodal models (LMMs) such as GPT-4V(ision). It consists of two main components: (1) A robust codebase that supports running web agents on live websites, and (2) an innovative framework that utilizes LMMs as generalist web agents.
Author-email: Boyu Gou <gou.43@osu.edu>, Boyuan Zheng <zheng.2372@osu.edu>, Zheng Du <du.913@osu.edu>
License: AI PUBS OPEN RAIL-S LICENSE
Project-URL: homepage, https://osu-nlp-group.github.io/SeeAct/
Project-URL: repository, https://github.com/OSU-NLP-Group/SeeAct
Project-URL: documentation, https://github.com/OSU-NLP-Group/SeeAct
Requires-Python: >=3.9
License-File: LICENSE
Requires-Dist: backoff
Requires-Dist: playwright
Requires-Dist: toml
Requires-Dist: openai==1.24.0
Requires-Dist: httpx==0.27.2
Requires-Dist: litellm==1.35.32
Requires-Dist: google-generativeai==0.5.2
Requires-Dist: python-dotenv
